ntrees_tuning/__init__.py
ntrees_tuning/_gradboost.py
ntrees_tuning/_randforest.py
ntrees_tuning/_utils.py
ntrees_tuning-0.1.1.dist-info/licenses/LICENSE
ntrees_tuning-0.1.1.dist-info/METADATA
ntrees_tuning-0.1.1.dist-info/WHEEL
ntrees_tuning-0.1.1.dist-info/top_level.txt
ntrees_tuning-0.1.1.dist-info/RECORD
