Metadata-Version: 2.4
Name: ntrees_tuning
Version: 0.1.1
Summary: The package ntrees_tuning is an extension to sklearn. To Random Forests and Gradient Boosting it adds the ntrees parameter which gives control over how many trees are used for prediction. The main benefit is that it enables to tune the ntrees parameter w.r.t. the OOB-error without having to retrain a new model for each value of ntrees.
Author-email: Schalwal <walmitschal@proton.me>
License-Expression: MIT
License-File: LICENSE
Requires-Dist: scikit-learn>=1.3.2
Requires-Dist: scipy>=1.7.0
Requires-Dist: numpy>=1.21.0
Provides-Extra: dev
Requires-Dist: pytest>=7.0; extra == "dev"
Dynamic: license-file
